countries_utils/__init__.py
countries_utils/countries_utils.py
countries_utils/countries_utils_unittest.py
countries_utils-1.0.21.dist-info/LICENSE
countries_utils-1.0.21.dist-info/METADATA
countries_utils-1.0.21.dist-info/WHEEL
countries_utils-1.0.21.dist-info/top_level.txt
countries_utils-1.0.21.dist-info/RECORD
