Metadata-Version: 2.1
Name: countries-utils
Version: 1.0.21
Summary: Utils to deal with pycountry and country_list packages
Home-page: https://bitbucket.org/altf1be/countries_utils.git
Author: Abdelkrim Boujraf
Author-email: abo+countries_utils_pkg@alt-f1.be
License: European Union Public Licence 1.2 (EUPL 1.2)
Project-URL: Bug Reports, https://bitbucket.org/altf1be/countries-utils/issues?status=new&status=open
Project-URL: Company behind the library, http://www.alt-f1.be
Project-URL: Source, https://bitbucket.org/altf1be/countries-utils
Keywords: library,pycountry,country_list,dunning_service,alt-f1.be
Platform: UNKNOWN
Classifier: Development Status :: 5 - Production/Stable
Classifier: Intended Audience :: Developers
Classifier: License :: OSI Approved :: European Union Public Licence 1.2 (EUPL 1.2)
Classifier: Operating System :: OS Independent
Classifier: Programming Language :: Python :: 3.7
Classifier: Topic :: Software Development :: Libraries :: Python Modules
Requires-Python: >=3.5
Requires-Dist: pycountry
Requires-Dist: pandas
Requires-Dist: country-list
